[
	{
		"tel": "18299258446",
		"points": "181",
		"name": "Joel Vargas"
	},
	{
		"tel": "18094382220",
		"points": "137",
		"name": "Daniel Tavera"
	},
	{
		"tel": "18492803016",
		"points": "116",
		"name": "Samuel Abreu"
	},
	{
		"tel": "18494020444",
		"points": "79",
		"name": "Junior Perez"
	},
	{
		"tel": "18297259689",
		"points": "75",
		"name": "Sulerka Tatis Pérez"
	},
	{
		"tel": "18296329931",
		"points": "75",
		"name": "Henry Paulino Velez"
	},
	{
		"tel": "18297010940",
		"points": "60",
		"name": "Jenn Rojas"
	},
	{
		"tel": "18287371332",
		"points": "56",
		"name": "Jarold De Leon"
	},
	{
		"tel": "18492063918",
		"points": "52",
		"name": "Alexandra Olivo"
	},
	{
		"tel": "18099678169",
		"points": "52",
		"name": "Wilmer Enmanuel"
	},
	{
		"tel": "18296404950",
		"points": "52",
		"name": "Daniela Zapata"
	},
	{
		"tel": "18492538563",
		"points": "52",
		"name": "Juan Michel Soriano"
	},
	{
		"tel": "18092174793",
		"points": "52",
		"name": "Eduardo Guerrero"
	},
	{
		"tel": "18492696003",
		"points": "52",
		"name": "Lazaro Camacho"
	},
	{
		"tel": "18492741014",
		"points": "50",
		"name": "Reyna Martinez"
	},
	{
		"tel": "18094199375",
		"points": "50",
		"name": "Mabel Arno Solis"
	},
	{
		"tel": "18094018209",
		"points": "50",
		"name": "Keren Abreu"
	},
	{
		"tel": "18094600420",
		"points": "50",
		"name": "Freddy Ernesto Montero Custodio"
	},
	{
		"tel": "18292306783",
		"points": "50",
		"name": "Emely Nina"
	},
	{
		"tel": "18293710419",
		"points": "50",
		"name": "Zoe Jiménez"
	},
	{
		"tel": "18298554138",
		"points": "50",
		"name": "Rosa Soto"
	},
	{
		"tel": "18093176755",
		"points": "50",
		"name": "Nicole Palmer"
	},
	{
		"tel": "18299346902",
		"points": "50",
		"name": "Yeimi Carrasco"
	},
	{
		"tel": "18498671803",
		"points": "50",
		"name": "Rosleidy Urbaez"
	},
	{
		"tel": "18294724480",
		"points": "50",
		"name": "Jhoan Rosario"
	},
	{
		"tel": "18292019966",
		"points": "50",
		"name": "Keysi Sención"
	},
	{
		"tel": "19852141755",
		"points": "37",
		"name": " "
	},
	{
		"tel": "18096140170",
		"points": "37",
		"name": "Willy Escolastico"
	},
	{
		"tel": "18293496606",
		"points": "31",
		"name": "Alondra Henriquez"
	},
	{
		"tel": "18492010798",
		"points": "29",
		"name": "Karla Jazmín"
	},
	{
		"tel": "18297192866",
		"points": "29",
		"name": "Jhonny López"
	},
	{
		"tel": "18494099755",
		"points": "29",
		"name": "Mariam Brand"
	},
	{
		"tel": "18496377830",
		"points": "29",
		"name": "Nore Espinoza"
	},
	{
		"tel": "18094379369",
		"points": "29",
		"name": "Mariel Brito"
	},
	{
		"tel": "18098278486",
		"points": "29",
		"name": "Madelin Sanchez"
	},
	{
		"tel": "18299801632",
		"points": "29",
		"name": "Sofía Troncoso"
	},
	{
		"tel": "18294070602",
		"points": "29",
		"name": "Jose Enrique"
	},
	{
		"tel": "18493538503",
		"points": "29",
		"name": "Maria Hiraldo"
	},
	{
		"tel": "18099675482",
		"points": "27",
		"name": "Sandra Guzmán Medina"
	},
	{
		"tel": "18294384807",
		"points": "27",
		"name": "Elyas Poueriet"
	},
	{
		"tel": "18292729910",
		"points": "27",
		"name": "Tania Capellan"
	},
	{
		"tel": "18293690358",
		"points": "27",
		"name": "John Wick"
	},
	{
		"tel": "18299032103",
		"points": "27",
		"name": "Jakaury Santana"
	},
	{
		"tel": "18496587274",
		"points": "27",
		"name": "Argenis Castro"
	},
	{
		"tel": "18296497678",
		"points": "27",
		"name": "Misael Peña"
	},
	{
		"tel": "18096101385",
		"points": "27",
		"name": "Clary Sandoval"
	},
	{
		"tel": "18293179822",
		"points": "27",
		"name": "Vianesa Lopez"
	},
	{
		"tel": "18299192503",
		"points": "27",
		"name": "Rebelio 3"
	},
	{
		"tel": "18297177966",
		"points": "27",
		"name": "Richard Sosa"
	},
	{
		"tel": "18293806767",
		"points": "27",
		"name": "Maria Nieves Mateo Calderon"
	},
	{
		"tel": "18092513724",
		"points": "27",
		"name": "Miguelina Madrigal"
	},
	{
		"tel": "18294139804",
		"points": "27",
		"name": "Yomeiry De La Cruz"
	},
	{
		"tel": "18499197721",
		"points": "27",
		"name": "Diosdeily Morel"
	},
	{
		"tel": "18298618992",
		"points": "27",
		"name": "Loxy Jimenez"
	},
	{
		"tel": "18098520302",
		"points": "27",
		"name": "Alicia Sarante"
	},
	{
		"tel": "18093599794",
		"points": "27",
		"name": "Emmanuel Blanco Solano"
	},
	{
		"tel": "18295428166",
		"points": "27",
		"name": "Berlis Rodriguez Severino"
	},
	{
		"tel": "18493422824",
		"points": "27",
		"name": "Perl Cep"
	},
	{
		"tel": "18097689077",
		"points": "27",
		"name": "Hector Rodriguez"
	},
	{
		"tel": "18298275932",
		"points": "27",
		"name": "Noemi Martinez"
	},
	{
		"tel": "18497518000",
		"points": "27",
		"name": "Ashly Heredia Hernandez"
	},
	{
		"tel": "18293326342",
		"points": "27",
		"name": " "
	},
	{
		"tel": "18097787341",
		"points": "27",
		"name": "Yanibell Cordero"
	},
	{
		"tel": "18295717519",
		"points": "27",
		"name": "Eliana Reyes Duran"
	},
	{
		"tel": "18099962366",
		"points": "27",
		"name": "Edwin Feliz"
	},
	{
		"tel": "18299311830",
		"points": "27",
		"name": "Alejandro Quezada"
	},
	{
		"tel": "18494596584",
		"points": "27",
		"name": "Manuel Cuesta"
	},
	{
		"tel": "18299222266",
		"points": "27",
		"name": "Willy Cruz"
	},
	{
		"tel": "18298569019",
		"points": "27",
		"name": "Odette Ferrer"
	},
	{
		"tel": "18095195857",
		"points": "27",
		"name": "Mildred Leiva"
	},
	{
		"tel": "18097152914",
		"points": "27",
		"name": "Natalie Tavarez"
	},
	{
		"tel": "18097774925",
		"points": "27",
		"name": "Nelly Caraballo"
	},
	{
		"tel": "18296425120",
		"points": "27",
		"name": "Nicole Báez Minyety"
	},
	{
		"tel": "18293241389",
		"points": "25",
		"name": "Mario G. "
	},
	{
		"tel": "18293157140",
		"points": "25",
		"name": "Randy Peres"
	},
	{
		"tel": "18298940053",
		"points": "25",
		"name": "Luis Zaera"
	},
	{
		"tel": "18292041213",
		"points": "25",
		"name": "Elena Aristy"
	},
	{
		"tel": "18297433296",
		"points": "25",
		"name": "Genisel Encarnación"
	},
	{
		"tel": "18492103299",
		"points": "25",
		"name": "Israel Encarnacion"
	},
	{
		"tel": "18299053294",
		"points": "25",
		"name": "Altagracia Feliz"
	},
	{
		"tel": "18098531075",
		"points": "25",
		"name": "Sory Alberto"
	},
	{
		"tel": "18492252630",
		"points": "25",
		"name": "Luis Canario"
	},
	{
		"tel": "18094197017",
		"points": "25",
		"name": "Yahayra Cumba"
	},
	{
		"tel": "18296733893",
		"points": "25",
		"name": "Jelkin Riveras"
	},
	{
		"tel": "18293764026",
		"points": "25",
		"name": "Yomasi Antonio Gonzalez Aecevdo"
	},
	{
		"tel": "18493189562",
		"points": "25",
		"name": "Wendy Rosado"
	},
	{
		"tel": "18095202147",
		"points": "25",
		"name": "Angel Perez"
	},
	{
		"tel": "18098757425",
		"points": "25",
		"name": "Jhonatan Soto"
	},
	{
		"tel": "18295182018",
		"points": "25",
		"name": "Michaell Hoepelman"
	},
	{
		"tel": "18293154353",
		"points": "25",
		"name": "Yudith Monserrrate"
	},
	{
		"tel": "18297134776",
		"points": "25",
		"name": "Grisel M Cabral"
	},
	{
		"tel": "18493449652",
		"points": "25",
		"name": "Elias Hdez"
	},
	{
		"tel": "18492842780",
		"points": "25",
		"name": "Mary Pily Rodriguez"
	},
	{
		"tel": "18493567495",
		"points": "25",
		"name": " "
	},
	{
		"tel": "18097148024",
		"points": "25",
		"name": "Luis Alberto Marmol De Leon"
	},
	{
		"tel": "18096097729",
		"points": "25",
		"name": "Grice Adames"
	},
	{
		"tel": "18299109076",
		"points": "25",
		"name": "Perla Osoria"
	},
	{
		"tel": "18094130201",
		"points": "25",
		"name": "Felix Guzmán"
	},
	{
		"tel": "18298683642",
		"points": "25",
		"name": "Juleysi Marizan"
	},
	{
		"tel": "18295615678",
		"points": "25",
		"name": "Abdiel Gomez"
	},
	{
		"tel": "18298368906",
		"points": "25",
		"name": "Smerth Charles"
	},
	{
		"tel": "18493538305",
		"points": "25",
		"name": "Scarlett Ramirez"
	},
	{
		"tel": "18094039361",
		"points": "25",
		"name": "Yamilka Castillo"
	},
	{
		"tel": "18099811322",
		"points": "25",
		"name": "Lenka ."
	},
	{
		"tel": "18099566978",
		"points": "25",
		"name": " "
	},
	{
		"tel": "18297151511",
		"points": "25",
		"name": "Yunior Garcia Corcino"
	},
	{
		"tel": "18292468605",
		"points": "25",
		"name": "Melany Aquino Medina"
	},
	{
		"tel": "18095179986",
		"points": "25",
		"name": "Manuel Marte Rosario"
	},
	{
		"tel": "18293814752",
		"points": "25",
		"name": "Gabriela "
	},
	{
		"tel": "18096012019",
		"points": "25",
		"name": "Yessica Padilla"
	},
	{
		"tel": "18295423459",
		"points": "25",
		"name": "Lisa Fuente"
	},
	{
		"tel": "18292636050",
		"points": "25",
		"name": "Elianna Hernández"
	},
	{
		"tel": "18299213644",
		"points": "25",
		"name": "David Ureña"
	},
	{
		"tel": "18093178284",
		"points": "25",
		"name": "Anthony Mercedes"
	},
	{
		"tel": "18497513610",
		"points": "25",
		"name": "Rosmailyn Cruceta"
	},
	{
		"tel": "18297841511",
		"points": "25",
		"name": "Yunior Garcia Corcino"
	},
	{
		"tel": "18094447847",
		"points": "25",
		"name": "Katty García"
	},
	{
		"tel": "18494021565",
		"points": "25",
		"name": "Brianna Montero"
	},
	{
		"tel": "18299275787",
		"points": "25",
		"name": "Nathalie Liriano"
	},
	{
		"tel": "18297804709",
		"points": "25",
		"name": "Melvin Gomez"
	},
	{
		"tel": "18296918130",
		"points": "25",
		"name": "Elianna Alexandra Ramirez"
	},
	{
		"tel": "18295722515",
		"points": "25",
		"name": "Carlos De Frías"
	},
	{
		"tel": "18294250267",
		"points": "25",
		"name": "Florangel N Rodriguez"
	},
	{
		"tel": "18099283979",
		"points": "25",
		"name": "Vladimir Miranda Perez"
	},
	{
		"tel": "18099974368",
		"points": "25",
		"name": "Johan R."
	},
	{
		"tel": "18492060894",
		"points": "25",
		"name": "Alberto Delgado"
	},
	{
		"tel": "18295879765",
		"points": "25",
		"name": "Jeeziel Gonzalez"
	},
	{
		"tel": "18298698344",
		"points": "25",
		"name": "Daniella Mella"
	},
	{
		"tel": "18293325891",
		"points": "25",
		"name": "Rosanna C.P"
	},
	{
		"tel": "18293050291",
		"points": "25",
		"name": "Ingrid Nicole Polanco Méndez"
	},
	{
		"tel": "18296584297",
		"points": "25",
		"name": "Leceli Jimenez Suaresz"
	},
	{
		"tel": "18097698344",
		"points": "25",
		"name": "Fatima Muñoz Morales"
	},
	{
		"tel": "18098495070",
		"points": "25",
		"name": "Johana Rodriguez"
	},
	{
		"tel": "18098030732",
		"points": "25",
		"name": "Geraldin Pineda"
	},
	{
		"tel": "13034794389",
		"points": "25",
		"name": "Daunys "
	},
	{
		"tel": "18497076558",
		"points": "25",
		"name": "Carlos Caminero"
	},
	{
		"tel": "18298859107",
		"points": "25",
		"name": "Luis Angel Acosta Gomez"
	},
	{
		"tel": "18296548325",
		"points": "25",
		"name": "Crisheily Grullard"
	},
	{
		"tel": "18096083889",
		"points": "25",
		"name": "Catalina Jiménez"
	},
	{
		"tel": "18299591688",
		"points": "25",
		"name": "Ashly Canelo"
	},
	{
		"tel": "18299806203",
		"points": "25",
		"name": "Alberto Bleyler"
	},
	{
		"tel": "18295481315",
		"points": "25",
		"name": "Simon David"
	},
	{
		"tel": "18098432653",
		"points": "25",
		"name": "Abigail Cabrera"
	},
	{
		"tel": "19782764913",
		"points": "25",
		"name": "Genauris Alcantara Dipre"
	},
	{
		"tel": "18299264664",
		"points": "25",
		"name": "Alberto Rivas H"
	},
	{
		"tel": "18297655010",
		"points": "25",
		"name": " "
	},
	{
		"tel": "18297404903",
		"points": "25",
		"name": "Raydel Suárez"
	},
	{
		"tel": "18497531367",
		"points": "25",
		"name": "Heine Lanfranco"
	},
	{
		"tel": "18292841293",
		"points": "25",
		"name": "Jose Ramon"
	},
	{
		"tel": "18295982651",
		"points": "25",
		"name": "Charina Collado"
	},
	{
		"tel": "18492120729",
		"points": "25",
		"name": "Jeyson Hernandez"
	},
	{
		"tel": "18299815953",
		"points": "25",
		"name": "Florangel Dominguez"
	},
	{
		"tel": "18493600052",
		"points": "25",
		"name": "Darwin Ferreyra"
	},
	{
		"tel": "18099860858",
		"points": "25",
		"name": "Jose Brito"
	},
	{
		"tel": "18293629872",
		"points": "25",
		"name": "Nino Acosta"
	},
	{
		"tel": "18295899588",
		"points": "25",
		"name": "Yamelin Perez Bello"
	},
	{
		"tel": "18094998119",
		"points": "25",
		"name": "Sophia Morla"
	},
	{
		"tel": "18294605301",
		"points": "25",
		"name": "Raydenis Encarnación"
	},
	{
		"tel": "18295921996",
		"points": "25",
		"name": "Joel Sena"
	},
	{
		"tel": "18098018893",
		"points": "25",
		"name": "Abril Pérez"
	},
	{
		"tel": "18299649570",
		"points": "25",
		"name": "Johan Peña"
	},
	{
		"tel": "18092589958",
		"points": "25",
		"name": "Maicol Manuel Jimenez Leonardo"
	},
	{
		"tel": "18097174727",
		"points": "25",
		"name": "Yerald Cuello Rondon"
	},
	{
		"tel": "18097805010",
		"points": "25",
		"name": "Sander Arias"
	},
	{
		"tel": "18297178768",
		"points": "25",
		"name": "Enrique Baez"
	},
	{
		"tel": "18097567249",
		"points": "25",
		"name": "Samantha Diaz"
	},
	{
		"tel": "18096183075",
		"points": "25",
		"name": "Mayre Liriano"
	},
	{
		"tel": "18294389844",
		"points": "25",
		"name": "Ninoska Mejia"
	},
	{
		"tel": "18298800850",
		"points": "25",
		"name": "Hade Öztürk"
	},
	{
		"tel": "18492583430",
		"points": "25",
		"name": "Sergio Piña"
	},
	{
		"tel": "18494538011",
		"points": "25",
		"name": "Karla Almonte Aquino"
	},
	{
		"tel": "18096499964",
		"points": "25",
		"name": "Yanely Sánchez"
	},
	{
		"tel": "18298358808",
		"points": "25",
		"name": "Yulianny Guzman"
	},
	{
		"tel": "18099682536",
		"points": "25",
		"name": "Ángel Montero"
	},
	{
		"tel": "18297663402",
		"points": "25",
		"name": "Esther Tejeda"
	},
	{
		"tel": "18094351234",
		"points": "25",
		"name": "Scarlin A.L"
	},
	{
		"tel": "18092713261",
		"points": "25",
		"name": "Andy Del Rosario"
	},
	{
		"tel": "18298636831",
		"points": "25",
		"name": "Bryan Saviñon"
	},
	{
		"tel": "18295572861",
		"points": "25",
		"name": "Magdelin Nicole Castillo Cuevas"
	},
	{
		"tel": "18296160392",
		"points": "25",
		"name": "Ailan Castillo"
	},
	{
		"tel": "18297086509",
		"points": "25",
		"name": "Odile Otano"
	},
	{
		"tel": "18293712066",
		"points": "25",
		"name": "Chandler Dotting"
	},
	{
		"tel": "18492010751",
		"points": "25",
		"name": "Bianca Made"
	},
	{
		"tel": "18094746916",
		"points": "25",
		"name": "Miguel Angel Lebron"
	},
	{
		"tel": "18297405544",
		"points": "25",
		"name": "Alexis Gómez"
	},
	{
		"tel": "18298584809",
		"points": "25",
		"name": "Sonia Perez"
	},
	{
		"tel": "18297887775",
		"points": "25",
		"name": "Ana Batista"
	},
	{
		"tel": "18295493155",
		"points": "25",
		"name": "Paola Martinez"
	},
	{
		"tel": "18298790991",
		"points": "25",
		"name": "Hadassa Jean Noël"
	},
	{
		"tel": "18096965881",
		"points": "25",
		"name": "Jenises Ramirez"
	},
	{
		"tel": "18298524228",
		"points": "25",
		"name": "Cristal Delgado"
	},
	{
		"tel": "18099146161",
		"points": "25",
		"name": "Kasandra Pecora"
	},
	{
		"tel": "18496520568",
		"points": "25",
		"name": "Danicha Severino"
	},
	{
		"tel": "18096661255",
		"points": "25",
		"name": "Leonel Figuereo"
	},
	{
		"tel": "18094332806",
		"points": "25",
		"name": "Lucía Ogando"
	},
	{
		"tel": "18299411953",
		"points": "25",
		"name": "Stalin Amparo"
	},
	{
		"tel": "18292832987",
		"points": "25",
		"name": "Licda Pena"
	},
	{
		"tel": "18097161193",
		"points": "25",
		"name": "Jeudi Alexandra Alcantara De La Cruz"
	},
	{
		"tel": "18498574120",
		"points": "25",
		"name": "Gilberto Aneudy Segura Ramirez"
	},
	{
		"tel": "18293437874",
		"points": "25",
		"name": "Emely Cabral"
	},
	{
		"tel": "18094652431",
		"points": "25",
		"name": "José Alberto Canario"
	},
	{
		"tel": "18492643268",
		"points": "25",
		"name": "Maria Saladin"
	},
	{
		"tel": "18492533524",
		"points": "25",
		"name": "Guadalupe Guzman Horacio"
	},
	{
		"tel": "18093024765",
		"points": "25",
		"name": "Michael Tiburcio"
	},
	{
		"tel": "18496548570",
		"points": "25",
		"name": " "
	},
	{
		"tel": "18498466927",
		"points": "25",
		"name": "Claudia Nolasco"
	},
	{
		"tel": "18099198799",
		"points": "25",
		"name": "Yinelis Esther Hernandez Morillo"
	},
	{
		"tel": "18496323260",
		"points": "25",
		"name": "Nataly Jose Carrasco"
	},
	{
		"tel": "18496324398",
		"points": "25",
		"name": "Yariel Méndez"
	},
	{
		"tel": "18292877265",
		"points": "25",
		"name": "Habier Elias Caraballo Ceballo"
	},
	{
		"tel": "18098813074",
		"points": "25",
		"name": "Yessa De La Cruz"
	},
	{
		"tel": "18093928911",
		"points": "25",
		"name": "Anyeli Alvarez"
	},
	{
		"tel": "18293778294",
		"points": "25",
		"name": "Angel Batista"
	},
	{
		"tel": "18098918968",
		"points": "25",
		"name": "Mayelin Santana"
	},
	{
		"tel": "18296458538",
		"points": "25",
		"name": "Carlos Lachapel"
	},
	{
		"tel": "18498604133",
		"points": "25",
		"name": "Daniel Alturo Mendez Medina"
	},
	{
		"tel": "18492207344",
		"points": "25",
		"name": "Jazmin Gonzalez"
	},
	{
		"tel": "18296788823",
		"points": "25",
		"name": "Iscaura Alcantara"
	},
	{
		"tel": "18297526952",
		"points": "25",
		"name": "Arturo Nina"
	},
	{
		"tel": "18092571103",
		"points": "25",
		"name": "Josue Melo Ventura"
	},
	{
		"tel": "18093941388",
		"points": "25",
		"name": "Ray Martinez"
	},
	{
		"tel": "18297781728",
		"points": "25",
		"name": "Eduardo Vasquez"
	},
	{
		"tel": "18295611989",
		"points": "25",
		"name": "Samuel Rojas"
	},
	{
		"tel": "18096101864",
		"points": "25",
		"name": "Andreisis Peralta"
	},
	{
		"tel": "18493531809",
		"points": "25",
		"name": "Dayanni Nunez"
	},
	{
		"tel": "18299094166",
		"points": "25",
		"name": "Luis Manuel Gomez Jose"
	},
	{
		"tel": "18097626441",
		"points": "25",
		"name": "Laura "
	},
	{
		"tel": "18295424669",
		"points": "25",
		"name": "Melissa Rodríguez"
	},
	{
		"tel": "18297784390",
		"points": "25",
		"name": "Lya Nathalia Pichardo Rivera"
	},
	{
		"tel": "18099772328",
		"points": "25",
		"name": "Dahyana Rodriguez"
	},
	{
		"tel": "18299705551",
		"points": "25",
		"name": "Cristina Martínez"
	},
	{
		"tel": "18093531783",
		"points": "25",
		"name": "Helen Gmz"
	},
	{
		"tel": "18296891710",
		"points": "25",
		"name": "Arismendy Gomez Cruz"
	},
	{
		"tel": "18292089334",
		"points": "25",
		"name": "Robert Nieve"
	},
	{
		"tel": "18297915533",
		"points": "25",
		"name": "Luis Daniel Rosario"
	},
	{
		"tel": "18294770022",
		"points": "25",
		"name": "Angel Sierra"
	},
	{
		"tel": "18299158668",
		"points": "25",
		"name": "Marco Sosa"
	},
	{
		"tel": "17792325166",
		"points": "25",
		"name": "Daniel Pastrana"
	},
	{
		"tel": "14352415433",
		"points": "25",
		"name": "Daniel Pastran"
	},
	{
		"tel": "18297647326",
		"points": "25",
		"name": "Anyie Vargas"
	},
	{
		"tel": "18097195237",
		"points": "25",
		"name": "Bichar Mal"
	},
	{
		"tel": "18295613783",
		"points": "25",
		"name": "Crisleyny Peña"
	},
	{
		"tel": "18499184299",
		"points": "25",
		"name": " "
	},
	{
		"tel": "18097616499",
		"points": "25",
		"name": "Heinse Pimentel"
	},
	{
		"tel": "18494067147",
		"points": "25",
		"name": "Rossy Perez"
	},
	{
		"tel": "18298065881",
		"points": "25",
		"name": "Andrea Alcántara"
	},
	{
		"tel": "18295874474",
		"points": "25",
		"name": "Vianny Vargas"
	},
	{
		"tel": "18494049258",
		"points": "25",
		"name": "Marcos Emiliano"
	},
	{
		"tel": "19736653925",
		"points": "25",
		"name": "Yefri "
	},
	{
		"tel": "18094390915",
		"points": "25",
		"name": "Heri Ramírez"
	},
	{
		"tel": "18297642880",
		"points": "25",
		"name": "Jenny Boitel Rosario"
	},
	{
		"tel": "18297292383",
		"points": "25",
		"name": "Eliana Santana"
	},
	{
		"tel": "18299695013",
		"points": "25",
		"name": "Yissel Cabrera"
	},
	{
		"tel": "18098559721",
		"points": "25",
		"name": "Cándida Marioliz Infante"
	},
	{
		"tel": "18099668174",
		"points": "25",
		"name": "Richard Amadis Robinson"
	},
	{
		"tel": "18292992087",
		"points": "25",
		"name": "Isabel Bautista"
	},
	{
		"tel": "18299227998",
		"points": "25",
		"name": "Yenny Zapata"
	},
	{
		"tel": "18298170233",
		"points": "25",
		"name": "Johan Lachapel"
	},
	{
		"tel": "18294221061",
		"points": "25",
		"name": "Jose Miguel Acosta"
	},
	{
		"tel": "18295912720",
		"points": "25",
		"name": "Leidy Perez Suarez"
	},
	{
		"tel": "18296160928",
		"points": "25",
		"name": "Yomairi Raposo"
	},
	{
		"tel": "18292968721",
		"points": "25",
		"name": "Yanilci Disla"
	},
	{
		"tel": "18296607854",
		"points": "25",
		"name": "Luis David"
	},
	{
		"tel": "18292841288",
		"points": "25",
		"name": "Nathhy Mena"
	},
	{
		"tel": "18292828056",
		"points": "25",
		"name": "Andreina Castillo"
	},
	{
		"tel": "18299082780",
		"points": "25",
		"name": "Yeidy Perez"
	},
	{
		"tel": "18097295848",
		"points": "25",
		"name": "Gabriel Acevedo"
	},
	{
		"tel": "18299834388",
		"points": "25",
		"name": "Gabriel Cotto"
	},
	{
		"tel": "18498655009",
		"points": "25",
		"name": "Soranyi Consuegra"
	},
	{
		"tel": "18097170037",
		"points": "25",
		"name": "Esther Franchesca"
	},
	{
		"tel": "18299903608",
		"points": "25",
		"name": "Yeraisa Paez"
	},
	{
		"tel": "18498160909",
		"points": "25",
		"name": "Edwin Luciano"
	},
	{
		"tel": "18097496025",
		"points": "25",
		"name": "John Gregoris Ferreras"
	},
	{
		"tel": "18297058406",
		"points": "25",
		"name": "Annelys Marmolejos Garcia"
	},
	{
		"tel": "18498613734",
		"points": "25",
		"name": "Jaferlin Morales"
	},
	{
		"tel": "18295525607",
		"points": "25",
		"name": "Jose Asmar"
	},
	{
		"tel": "18297286932",
		"points": "25",
		"name": "Addiel Taveras"
	},
	{
		"tel": "18294404903",
		"points": "25",
		"name": "Elqsabe Garcia"
	},
	{
		"tel": "15012353434",
		"points": "25",
		"name": "Odalisa T."
	},
	{
		"tel": "18099661661",
		"points": "25",
		"name": "Andrea De Los Santos"
	},
	{
		"tel": "18494057786",
		"points": "25",
		"name": "Ana Josefina Pérez Dominguez"
	},
	{
		"tel": "18094463926",
		"points": "25",
		"name": "Juan Araujo"
	},
	{
		"tel": "18097909127",
		"points": "25",
		"name": "Acrilic Nails Teresa"
	},
	{
		"tel": "18299891830",
		"points": "25",
		"name": "Karen Cornelio"
	},
	{
		"tel": "18293972564",
		"points": "25",
		"name": "Kirsys Gomez"
	},
	{
		"tel": "18498584823",
		"points": "25",
		"name": "Alffi Núñez"
	},
	{
		"tel": "18298815040",
		"points": "25",
		"name": "Leslye Delgado"
	},
	{
		"tel": "18299734323",
		"points": "25",
		"name": "Ingrid Rosaly Nova Ledesma"
	},
	{
		"tel": "18097673550",
		"points": "25",
		"name": "Sara Sara Eodriguez"
	},
	{
		"tel": "18298999149",
		"points": "25",
		"name": "Freddy Marte"
	},
	{
		"tel": "12566499013",
		"points": "24",
		"name": "Nezay Sosel"
	},
	{
		"tel": "18094022294",
		"points": "24",
		"name": "Idelfonso Bencosme Diaz"
	},
	{
		"tel": "18098519825",
		"points": "16",
		"name": "Eglis 101"
	},
	{
		"tel": "18093918915",
		"points": "14",
		"name": "Cameron Victoria"
	},
	{
		"tel": "18296860091",
		"points": "12",
		"name": "Lorenzo Marte"
	},
	{
		"tel": "18096762629",
		"points": "12",
		"name": " "
	},
	{
		"tel": "18297264416",
		"points": "10",
		"name": "Leudis Cortorreal"
	},
	{
		"tel": "18298545416",
		"points": "10",
		"name": "Emilio A Perez"
	},
	{
		"tel": "18134306091",
		"points": "10",
		"name": "Mariel Ortiz"
	},
	{
		"tel": "18093867103",
		"points": "10",
		"name": "Andy Rosario"
	},
	{
		"tel": "18492757922",
		"points": "8",
		"name": "Raferly Amparo"
	},
	{
		"tel": "18492603512",
		"points": "8",
		"name": "Erika Lora"
	},
	{
		"tel": "18498651689",
		"points": "8",
		"name": "Eneroliza Del Carmen Mena"
	},
	{
		"tel": "18098869391",
		"points": "6",
		"name": "Edwin Mora"
	},
	{
		"tel": "18494043369",
		"points": "6",
		"name": "Yina Toribio"
	},
	{
		"tel": "18297154158",
		"points": "6",
		"name": "Génesis Cornielle"
	},
	{
		"tel": "19736684955",
		"points": "6",
		"name": "Robert Garcia"
	},
	{
		"tel": "18096536346",
		"points": "6",
		"name": "Silvestre Torres"
	},
	{
		"tel": "18093183834",
		"points": "6",
		"name": "Ferneliz F"
	},
	{
		"tel": "18295046213",
		"points": "6",
		"name": "Mary Feliz"
	},
	{
		"tel": "18299903126",
		"points": "6",
		"name": "Danny Manuel Calzado"
	},
	{
		"tel": "18492066094",
		"points": "4",
		"name": "Altagracia Delgado"
	},
	{
		"tel": "18496569609",
		"points": "4",
		"name": "Frank Aybar"
	},
	{
		"tel": "18093059242",
		"points": "4",
		"name": "Karin Ortiz"
	},
	{
		"tel": "18498032814",
		"points": "4",
		"name": "Omar Jose Canela"
	},
	{
		"tel": "18295926129",
		"points": "4",
		"name": "Luigi Rodríguez"
	},
	{
		"tel": "18094515566",
		"points": "4",
		"name": "Jessica Ortiz"
	},
	{
		"tel": "18099235443",
		"points": "4",
		"name": "Samuel Valverde 28"
	},
	{
		"tel": "18094394494",
		"points": "4",
		"name": "Edwin Dariberto Rodríguez Mateo"
	},
	{
		"tel": "18294507239",
		"points": "4",
		"name": "Oleysha Vic"
	},
	{
		"tel": "18298850166",
		"points": "4",
		"name": "Joel A Cordero A"
	},
	{
		"tel": "18492210112",
		"points": "4",
		"name": "Chris Montes De Oca"
	},
	{
		"tel": "18492104377",
		"points": "4",
		"name": "Jose Agustin Almonte"
	},
	{
		"tel": "18293133184",
		"points": "4",
		"name": "Miguel Arturo"
	},
	{
		"tel": "18093250037",
		"points": "4",
		"name": "Bianca Santamaria"
	},
	{
		"tel": "18297418460",
		"points": "4",
		"name": "Yariza Olivo Vidal"
	},
	{
		"tel": "18297408003",
		"points": "4",
		"name": "Johanna Mendez"
	},
	{
		"tel": "18094093681",
		"points": "4",
		"name": "Mariut De La Rosa"
	},
	{
		"tel": "18298476203",
		"points": "4",
		"name": "Yokairis Gonzalez"
	},
	{
		"tel": "18297018158",
		"points": "4",
		"name": "K Mdz"
	},
	{
		"tel": "18293520051",
		"points": "4",
		"name": "Jose Perez"
	},
	{
		"tel": "18098990864",
		"points": "4",
		"name": " "
	},
	{
		"tel": "18292622783",
		"points": "4",
		"name": "Kerlin Taveras"
	},
	{
		"tel": "18292891814",
		"points": "4",
		"name": "Celeni Guerrero"
	},
	{
		"tel": "18299577452",
		"points": "4",
		"name": "Yudith Pimentel"
	},
	{
		"tel": "18493530554",
		"points": "4",
		"name": "Eduardo Antonio Olivares Meléndez"
	},
	{
		"tel": "18098390529",
		"points": "4",
		"name": "Rosanna Diaz"
	},
	{
		"tel": "18295874483",
		"points": "4",
		"name": "Aurelisa Veloz"
	},
	{
		"tel": "18294596660",
		"points": "4",
		"name": "Yosmeilin Ramírez"
	},
	{
		"tel": "18298485719",
		"points": "4",
		"name": "Grecia María Verás Hernandez"
	},
	{
		"tel": "18099247068",
		"points": "4",
		"name": "Ivan Ramirez De Leon"
	},
	{
		"tel": "18292769027",
		"points": "4",
		"name": "Franklin Peña"
	},
	{
		"tel": "18299945449",
		"points": "4",
		"name": "Walker Novas Garo"
	},
	{
		"tel": "18295874423",
		"points": "4",
		"name": "Nayely De Asis"
	},
	{
		"tel": "18296467961",
		"points": "4",
		"name": "Erika Miranda"
	},
	{
		"tel": "18492101399",
		"points": "4",
		"name": "Desire Morillo"
	},
	{
		"tel": "18297575912",
		"points": "4",
		"name": "Yris Frías"
	},
	{
		"tel": "18298108824",
		"points": "4",
		"name": "Mindry De Leon"
	},
	{
		"tel": "18092668985",
		"points": "4",
		"name": "Janka Gonzalez"
	},
	{
		"tel": "18098145202",
		"points": "4",
		"name": "Abel Morel"
	},
	{
		"tel": "18299121629",
		"points": "4",
		"name": "Yadelis Feliz"
	},
	{
		"tel": "18094631502",
		"points": "4",
		"name": "Blacky Montana"
	},
	{
		"tel": "18296537874",
		"points": "4",
		"name": "Aris Del Jesus"
	},
	{
		"tel": "18498674401",
		"points": "4",
		"name": "Antoni Valdez"
	},
	{
		"tel": "18298819865",
		"points": "4",
		"name": "Durant Durant"
	},
	{
		"tel": "18295926998",
		"points": "4",
		"name": "Edwin R.R"
	},
	{
		"tel": "18299104237",
		"points": "4",
		"name": "Charina Mendez"
	},
	{
		"tel": "18294408068",
		"points": "4",
		"name": "Annddy Reyes"
	},
	{
		"tel": "18294402105",
		"points": "4",
		"name": "Rochel Doñe"
	},
	{
		"tel": "17206234396",
		"points": "4",
		"name": "Betty Paz"
	},
	{
		"tel": "18299121523",
		"points": "4",
		"name": "Yasiris Gonzalez"
	},
	{
		"tel": "18098809650",
		"points": "4",
		"name": "Rosa Elba Garcia Henriquez"
	},
	{
		"tel": "18292487841",
		"points": "2",
		"name": "David Genao"
	},
	{
		"tel": "18096018492",
		"points": "2",
		"name": "Yafreisy Lora Diaz"
	},
	{
		"tel": "18297807807",
		"points": "2",
		"name": "Jose Eduardo Mora De La Rosa"
	},
	{
		"tel": "18294706693",
		"points": "2",
		"name": "Emiliana Ferreras"
	},
	{
		"tel": "18296517283",
		"points": "2",
		"name": "Alba Payano"
	},
	{
		"tel": "18298987495",
		"points": "2",
		"name": "Franklin Peña"
	},
	{
		"tel": "18093177451",
		"points": "2",
		"name": "Ariel Sierra"
	},
	{
		"tel": "18097778178",
		"points": "2",
		"name": "Nelly Duran"
	},
	{
		"tel": "18498899162",
		"points": "2",
		"name": "Kevin Martez"
	},
	{
		"tel": "18093090027",
		"points": "2",
		"name": "Yandel Veras"
	},
	{
		"tel": "18497072470",
		"points": "2",
		"name": "Jostin Santiago"
	},
	{
		"tel": "18492453592",
		"points": "2",
		"name": "Karen Garcia"
	},
	{
		"tel": "18098586615",
		"points": "2",
		"name": "Lucero Moreta"
	},
	{
		"tel": "18295131687",
		"points": "2",
		"name": "Shelley Soler"
	},
	{
		"tel": "18293051467",
		"points": "2",
		"name": "Crisleidy Esteva"
	},
	{
		"tel": "18492198360",
		"points": "2",
		"name": "Gabriel Leyba"
	},
	{
		"tel": "18293673407",
		"points": "2",
		"name": "Carhen Chirinos"
	},
	{
		"tel": "18293496112",
		"points": "2",
		"name": "Raquel Vasquez"
	},
	{
		"tel": "18098643560",
		"points": "2",
		"name": "Ofrania Garcia"
	},
	{
		"tel": "18094190581",
		"points": "2",
		"name": "Cristina Cabrera"
	},
	{
		"tel": "18094200969",
		"points": "2",
		"name": "Andres Martinez"
	},
	{
		"tel": "18299687393",
		"points": "2",
		"name": "Leo Sandy"
	},
	{
		"tel": "18497631508",
		"points": "2",
		"name": "Yudith Medina"
	},
	{
		"tel": "18099750865",
		"points": "2",
		"name": "Scarlett Martinez"
	},
	{
		"tel": "18298662931",
		"points": "2",
		"name": "Wes Rodriguez"
	},
	{
		"tel": "18098209163",
		"points": "2",
		"name": "Perla Rivas"
	},
	{
		"tel": "18293903677",
		"points": "2",
		"name": "Eli R."
	},
	{
		"tel": "18298864950",
		"points": "2",
		"name": "Ingrid Pasible Cayetano"
	},
	{
		"tel": "18293416711",
		"points": "2",
		"name": "Gina Espaillat"
	},
	{
		"tel": "18497202771",
		"points": "2",
		"name": "Jhennari Rodríguez"
	},
	{
		"tel": "18299823555",
		"points": "2",
		"name": "Anny Gb"
	},
	{
		"tel": "18294424043",
		"points": "2",
		"name": "Yesenia Gomez"
	},
	{
		"tel": "18295795170",
		"points": "2",
		"name": "Brisel Pérez Lora"
	},
	{
		"tel": "18493524013",
		"points": "2",
		"name": "Sophyber Martinez"
	},
	{
		"tel": "18492605054",
		"points": "2",
		"name": "Edgar Montero"
	},
	{
		"tel": "18293757785",
		"points": "2",
		"name": "Franclin Castro"
	},
	{
		"tel": "18099144569",
		"points": "2",
		"name": "Diana Garcia"
	},
	{
		"tel": "18098393595",
		"points": "2",
		"name": "Luis Enrique Montero Del Rosario"
	},
	{
		"tel": "18098649611",
		"points": "2",
		"name": "Eliezer Manzueta Disla"
	},
	{
		"tel": "18297207723",
		"points": "2",
		"name": "Cindy Castillo"
	},
	{
		"tel": "18099655459",
		"points": "2",
		"name": "Zobeida Diaz"
	},
	{
		"tel": "18099836277",
		"points": "2",
		"name": "Harlen Heredia"
	},
	{
		"tel": "18093022104",
		"points": "2",
		"name": "Emelituerys Concepción"
	},
	{
		"tel": "18297012575",
		"points": "2",
		"name": "Yomery Marte"
	},
	{
		"tel": "18297296254",
		"points": "2",
		"name": "Emilio De Lo Santo"
	},
	{
		"tel": "18299448234",
		"points": "2",
		"name": "Massielle Silvestre"
	},
	{
		"tel": "18498781236",
		"points": "2",
		"name": "Yomar Bautista Encarnación"
	},
	{
		"tel": "18498764763",
		"points": "2",
		"name": "Catherine Saony Paredes"
	},
	{
		"tel": "18096577937",
		"points": "2",
		"name": "Lisseth Encarnacion"
	},
	{
		"tel": "18093033363",
		"points": "2",
		"name": "Wendy Vasquez"
	},
	{
		"tel": "18492677115",
		"points": "2",
		"name": "Marlen Díaz Estrella"
	},
	{
		"tel": "18496577766",
		"points": "2",
		"name": "Andreisa Constanzo Mateo"
	},
	{
		"tel": "18294085100",
		"points": "2",
		"name": "Francisco Vasquez Vasquez"
	},
	{
		"tel": "18098912895",
		"points": "2",
		"name": "Suleiny De La Rosa"
	},
	{
		"tel": "18296983099",
		"points": "2",
		"name": "Chanel Patricioluisa"
	},
	{
		"tel": "18099956326",
		"points": "2",
		"name": "Sebastian Sanchez Reyna"
	},
	{
		"tel": "18098829502",
		"points": "2",
		"name": "Sandy Javier Chalas"
	},
	{
		"tel": "18294181828",
		"points": "2",
		"name": "H Ddaniels"
	},
	{
		"tel": "18296060214",
		"points": "2",
		"name": "Liz Tamayo"
	},
	{
		"tel": "18297422411",
		"points": "2",
		"name": "Heather Camill"
	},
	{
		"tel": "18295664224",
		"points": "2",
		"name": "Ney Calcagno"
	},
	{
		"tel": "18098685650",
		"points": "2",
		"name": "Asheley Reyes"
	},
	{
		"tel": "18298352609",
		"points": "2",
		"name": "Mella Liz"
	},
	{
		"tel": "18297155046",
		"points": "2",
		"name": "Daruwin Matos"
	},
	{
		"tel": "18092602008",
		"points": "2",
		"name": "Sorange Espinosa"
	},
	{
		"tel": "18095071794",
		"points": "2",
		"name": "Luis Jose Moreno"
	},
	{
		"tel": "18298853265",
		"points": "2",
		"name": "Roy Cabrera"
	},
	{
		"tel": "18097564271",
		"points": "2",
		"name": "Michael Brito"
	},
	{
		"tel": "18098667758",
		"points": "2",
		"name": "Leonardo Lahoz"
	},
	{
		"tel": "18096721293",
		"points": "2",
		"name": "Anny Santana"
	},
	{
		"tel": "18298879144",
		"points": "2",
		"name": "Mercedes Martinez"
	},
	{
		"tel": "18096690914",
		"points": "2",
		"name": "Amelia Concepcion"
	},
	{
		"tel": "18298754009",
		"points": "2",
		"name": "Nahomi Encarnacion"
	},
	{
		"tel": "18297529265",
		"points": "2",
		"name": "Tanya Carolina Vargas"
	},
	{
		"tel": "18296626006",
		"points": "2",
		"name": "Sinaylin Gonzalez Guance"
	},
	{
		"tel": "13174834586",
		"points": "2",
		"name": "Bautista Belen"
	},
	{
		"tel": "18097435777",
		"points": "2",
		"name": "Favir Montero"
	},
	{
		"tel": "18297210697",
		"points": "2",
		"name": "Cristy Luna"
	},
	{
		"tel": "17197720206",
		"points": "2",
		"name": "Mohamed Tuezka"
	},
	{
		"tel": "18098410040",
		"points": "2",
		"name": "Ingrid Martinez"
	},
	{
		"tel": "18098048994",
		"points": "2",
		"name": "Oneiris Cuello"
	},
	{
		"tel": "18098017124",
		"points": "2",
		"name": "Helga Gabirondo"
	},
	{
		"tel": "18295694717",
		"points": "2",
		"name": "Luis Acosta"
	},
	{
		"tel": "18093581632",
		"points": "2",
		"name": "Yasmirna Benitez"
	},
	{
		"tel": "18498174052",
		"points": "2",
		"name": "Raudy Santos"
	},
	{
		"tel": "18094740052",
		"points": "2",
		"name": "Wendy Catalina Melo"
	},
	{
		"tel": "18492095557",
		"points": "2",
		"name": "Dionarys Santana Santana"
	},
	{
		"tel": "18297986836",
		"points": "2",
		"name": "Dyango Polanco"
	},
	{
		"tel": "18494539936",
		"points": "2",
		"name": "Juan Alvarez"
	},
	{
		"tel": "18098605342",
		"points": "2",
		"name": "Ailyn Encarnacion"
	},
	{
		"tel": "18492701677",
		"points": "2",
		"name": "Amber Soto"
	},
	{
		"tel": "18094085010",
		"points": "2",
		"name": "Neftali Taveras Acevedo"
	},
	{
		"tel": "18093760965",
		"points": "2",
		"name": "Aleany Matos"
	},
	{
		"tel": "18494050552",
		"points": "2",
		"name": "Priscila Santana"
	},
	{
		"tel": "18098601017",
		"points": "2",
		"name": "Yinelis Esther Hernandez Morillo"
	},
	{
		"tel": "18295910113",
		"points": "2",
		"name": "Julio Cesar Mendez"
	},
	{
		"tel": "18298746387",
		"points": "2",
		"name": "Ivan Santos"
	},
	{
		"tel": "18099355939",
		"points": "2",
		"name": "Diansy Vasquez"
	},
	{
		"tel": "18297872531",
		"points": "2",
		"name": "Argenys Del Orbe"
	},
	{
		"tel": "18293341857",
		"points": "2",
		"name": "Vic Galva"
	},
	{
		"tel": "18294770713",
		"points": "2",
		"name": "Masquiel ."
	},
	{
		"tel": "18293080933",
		"points": "2",
		"name": "Daris D. Segura"
	},
	{
		"tel": "18297072282",
		"points": "2",
		"name": "Julio Caba"
	},
	{
		"tel": "18097604382",
		"points": "2",
		"name": "Belinda Salcedo"
	},
	{
		"tel": "18492850863",
		"points": "2",
		"name": "Eleisida Padilla"
	},
	{
		"tel": "18497631166",
		"points": "2",
		"name": "Sandro Escarlante"
	},
	{
		"tel": "18292866593",
		"points": "2",
		"name": "Yeremi Gutierrez"
	},
	{
		"tel": "18298042435",
		"points": "2",
		"name": "Estefany Severino"
	},
	{
		"tel": "18093508300",
		"points": "2",
		"name": "Oscar "
	},
	{
		"tel": "18496561222",
		"points": "2",
		"name": "Bryan Rincon"
	},
	{
		"tel": "18098393795",
		"points": "2",
		"name": "Mario Yunior Toribio"
	},
	{
		"tel": "18494599284",
		"points": "2",
		"name": "Mariel Guzman"
	},
	{
		"tel": "18297036016",
		"points": "2",
		"name": "Rainel Ramirez"
	},
	{
		"tel": "18294045661",
		"points": "2",
		"name": "Ashmyr Paul"
	},
	{
		"tel": "18094010802",
		"points": "2",
		"name": "Dominic Melo #15"
	},
	{
		"tel": "18297261082",
		"points": "2",
		"name": "Wilbert Martes"
	},
	{
		"tel": "18097135378",
		"points": "2",
		"name": "Yudith Pichardo Reynoso"
	},
	{
		"tel": "18092806388",
		"points": "2",
		"name": "Delio Omar Cespedes Medina"
	},
	{
		"tel": "18098858107",
		"points": "2",
		"name": "Fabio Espinal"
	},
	{
		"tel": "18295607278",
		"points": "2",
		"name": "Raul Martinez"
	},
	{
		"tel": "18297829577",
		"points": "2",
		"name": "Euri Rojas"
	},
	{
		"tel": "18097511519",
		"points": "2",
		"name": "Willys Garcia"
	},
	{
		"tel": "18293565496",
		"points": "2",
		"name": "Luis De Peña Kelly"
	},
	{
		"tel": "18298941904",
		"points": "2",
		"name": "Nelson Pulido"
	},
	{
		"tel": "18098973431",
		"points": "2",
		"name": "Delis Encarnacion"
	},
	{
		"tel": "18098866633",
		"points": "2",
		"name": "Estefany Faña"
	},
	{
		"tel": "18492489862",
		"points": "2",
		"name": "Rosa Azcona"
	},
	{
		"tel": "18097427889",
		"points": "2",
		"name": "Alicia Moreta"
	},
	{
		"tel": "18094855857",
		"points": "2",
		"name": "Rosalía Moreno Feliz"
	},
	{
		"tel": "18097189482",
		"points": "2",
		"name": "Karol Garcia"
	},
	{
		"tel": "18099526042",
		"points": "2",
		"name": "Jose Alberto"
	},
	{
		"tel": "18092660359",
		"points": "2",
		"name": "Luz Rodriguez"
	},
	{
		"tel": "18096190135",
		"points": "2",
		"name": "Yinett Cabrera Familia"
	},
	{
		"tel": "18299790813",
		"points": "2",
		"name": "Damaris Feliz"
	},
	{
		"tel": "18295066082",
		"points": "2",
		"name": "Diandra Lora"
	},
	{
		"tel": "18292531001",
		"points": "2",
		"name": "Ranfery Hustle"
	},
	{
		"tel": "18296911292",
		"points": "2",
		"name": " "
	},
	{
		"tel": "18299398155",
		"points": "2",
		"name": "Karismel Medina"
	},
	{
		"tel": "18094087770",
		"points": "2",
		"name": "Argenis Pichardo"
	},
	{
		"tel": "18096961308",
		"points": "2",
		"name": "Maria Amelia Hache Nadal"
	},
	{
		"tel": "18292817223",
		"points": "2",
		"name": "Lisbet Encarnacion"
	},
	{
		"tel": "18293792785",
		"points": "2",
		"name": "Yordi Sena"
	},
	{
		"tel": "18297258630",
		"points": "2",
		"name": "Esmerlin Caraballo"
	},
	{
		"tel": "18297214892",
		"points": "2",
		"name": "Carmen Lora"
	},
	{
		"tel": "12013086166",
		"points": "2",
		"name": "Yeli "
	},
	{
		"tel": "18298692405",
		"points": "2",
		"name": "Nashla Rosario"
	},
	{
		"tel": "18299025015",
		"points": "2",
		"name": "La Tentacion Selvatica"
	},
	{
		"tel": "18295723678",
		"points": "2",
		"name": "Chedelet Dupreux"
	},
	{
		"tel": "18297293541",
		"points": "2",
		"name": "Dachira Baez"
	},
	{
		"tel": "18297280293",
		"points": "2",
		"name": "Darlene De Los Santos"
	},
	{
		"tel": "18098544904",
		"points": "2",
		"name": "Esmeralda Hernandez Moreno"
	},
	{
		"tel": "18296865348",
		"points": "2",
		"name": "Ashley Peña"
	},
	{
		"tel": "18492822558",
		"points": "2",
		"name": "Jendry Guzman Ramirez"
	},
	{
		"tel": "18293369942",
		"points": "2",
		"name": "Paul Arsenio De La Rosa Rodríguez"
	},
	{
		"tel": "18096624471",
		"points": "2",
		"name": "Nayely Rodríguez"
	},
	{
		"tel": "18297528283",
		"points": "2",
		"name": "Itania Johannes"
	},
	{
		"tel": "18093934212",
		"points": "2",
		"name": "Carolin Canela"
	},
	{
		"tel": "18292791098",
		"points": "2",
		"name": " "
	},
	{
		"tel": "18098166684",
		"points": "2",
		"name": "Jackson Aramburu"
	},
	{
		"tel": "18099190278",
		"points": "2",
		"name": "Emilio Jose Melo Pujols"
	},
	{
		"tel": "18099015223",
		"points": "2",
		"name": "Dwight Hernandez"
	},
	{
		"tel": "18097138434",
		"points": "2",
		"name": "Selena Rodriguez"
	},
	{
		"tel": "18299290401",
		"points": "2",
		"name": "Lisvet Mendez"
	},
	{
		"tel": "18099691722",
		"points": "2",
		"name": "Karina Medina"
	},
	{
		"tel": "18295606809",
		"points": "2",
		"name": "Regisma Kerlande"
	},
	{
		"tel": "18298415739",
		"points": "2",
		"name": "Nallely Montero"
	},
	{
		"tel": "18099723889",
		"points": "2",
		"name": "Kelvin Ant Salazar"
	},
	{
		"tel": "18098488707",
		"points": "2",
		"name": "Nathaly Ramírez"
	},
	{
		"tel": "18298047159",
		"points": "2",
		"name": "Luz Calderón"
	},
	{
		"tel": "18297472986",
		"points": "2",
		"name": "Raquel Garcia"
	},
	{
		"tel": "18098287358",
		"points": "2",
		"name": "Indhira Flores"
	},
	{
		"tel": "18299202357",
		"points": "2",
		"name": "Dionibel Sanchez"
	},
	{
		"tel": "18299836665",
		"points": "2",
		"name": "Yoban De Leon"
	},
	{
		"tel": "18296702440",
		"points": "2",
		"name": "Daniel Montero"
	},
	{
		"tel": "18097187945",
		"points": "2",
		"name": "Winifer Mejia"
	},
	{
		"tel": "18096078014",
		"points": "2",
		"name": "Alba Castro"
	},
	{
		"tel": "18097580495",
		"points": "2",
		"name": "Carolin Beltre"
	},
	{
		"tel": "18295397012",
		"points": "2",
		"name": "Cristhofer Hernandez"
	},
	{
		"tel": "18492064318",
		"points": "2",
		"name": "Eliezel Custodio"
	},
	{
		"tel": "18299607755",
		"points": "2",
		"name": "Madelayne Villa"
	},
	{
		"tel": "18295600081",
		"points": "2",
		"name": "Lao Puello"
	},
	{
		"tel": "18099064251",
		"points": "2",
		"name": "Lenin Miguel Montero"
	},
	{
		"tel": "18294599666",
		"points": "2",
		"name": "Carmen Guillen"
	},
	{
		"tel": "18099657945",
		"points": "2",
		"name": "Ligia Martinez"
	},
	{
		"tel": "18094400181",
		"points": "2",
		"name": "Francisco De La Nieve"
	},
	{
		"tel": "18493595844",
		"points": "2",
		"name": "Esequiel Matos"
	},
	{
		"tel": "18299222820",
		"points": "2",
		"name": "Raymil Eskiel Matos Infante"
	},
	{
		"tel": "18099494535",
		"points": "2",
		"name": "Elizabeth Arias"
	},
	{
		"tel": "18296488537",
		"points": "2",
		"name": "Gisselle Aquino"
	},
	{
		"tel": "14086382030",
		"points": "2",
		"name": "Mario Per"
	},
	{
		"tel": "18493526233",
		"points": "2",
		"name": "Karen Cristiana"
	},
	{
		"tel": "15103560350",
		"points": "2",
		"name": "Víctor Robles"
	},
	{
		"tel": "18093089251",
		"points": "2",
		"name": "Marielys Castellanos Garcia"
	},
	{
		"tel": "18295878328",
		"points": "2",
		"name": "Lusergis Moreta Aquino"
	},
	{
		"tel": "18094492896",
		"points": "2",
		"name": "Margarita Garcia"
	},
	{
		"tel": "18498031987",
		"points": "2",
		"name": "Elizabeth Medrano"
	},
	{
		"tel": "18293403098",
		"points": "2",
		"name": "Liandy Alb. L."
	},
	{
		"tel": "18094023491",
		"points": "2",
		"name": "Raylin Mejia"
	},
	{
		"tel": "18094271567",
		"points": "2",
		"name": "Laysa Espinal"
	},
	{
		"tel": "18096134070",
		"points": "2",
		"name": "Evan Martinez"
	},
	{
		"tel": "18095126484",
		"points": "2",
		"name": "Streisy Abreu"
	},
	{
		"tel": "18093191126",
		"points": "2",
		"name": "Rosa Iris Reyes"
	},
	{
		"tel": "18095018864",
		"points": "2",
		"name": "Christian Hart"
	},
	{
		"tel": "18492857170",
		"points": "2",
		"name": "Samuel Cuesta"
	},
	{
		"tel": "18295331331",
		"points": "2",
		"name": "Ti Marat"
	},
	{
		"tel": "18098499314",
		"points": "2",
		"name": "Annis Martinez"
	},
	{
		"tel": "18096343554",
		"points": "2",
		"name": "Dilia "
	},
	{
		"tel": "18296481359",
		"points": "2",
		"name": "Maximo Diaz"
	},
	{
		"tel": "18298555695",
		"points": "2",
		"name": "Leidy Calzado"
	},
	{
		"tel": "18295053269",
		"points": "2",
		"name": "Alexander Ureña"
	},
	{
		"tel": "18099659415",
		"points": "2",
		"name": " "
	},
	{
		"tel": "18093894047",
		"points": "2",
		"name": "Leslie Ruiz"
	},
	{
		"tel": "18295598872",
		"points": "2",
		"name": "Rosmelis Sanchez"
	},
	{
		"tel": "18094070585",
		"points": "2",
		"name": "Aashe De La Rosa"
	},
	{
		"tel": "18297294918",
		"points": "2",
		"name": "Nicol Benítez Wallace"
	},
	{
		"tel": "18093766065",
		"points": "2",
		"name": "Mariela Mariela"
	},
	{
		"tel": "18494019612",
		"points": "2",
		"name": "Dariel Reyes"
	},
	{
		"tel": "18298050892",
		"points": "2",
		"name": "Mariela Arias Mateo"
	},
	{
		"tel": "18292862026",
		"points": "2",
		"name": "Yuliana Ramirez"
	},
	{
		"tel": "18494594124",
		"points": "2",
		"name": "Isabell Diaz"
	},
	{
		"tel": "18094158800",
		"points": "2",
		"name": "Francis Alexander Hernandez Martinez"
	},
	{
		"tel": "18298632645",
		"points": "2",
		"name": "Wendoly Rosario"
	},
	{
		"tel": "18298877885",
		"points": "2",
		"name": "Smerlyn Castillo"
	},
	{
		"tel": "18299142802",
		"points": "2",
		"name": "Yocasta Lapaix"
	},
	{
		"tel": "18098812031",
		"points": "2",
		"name": "Yerami Perez"
	},
	{
		"tel": "18498035032",
		"points": "2",
		"name": "Naraby Pimentel Rodriguez"
	},
	{
		"tel": "18299852235",
		"points": "2",
		"name": "Sofia Sanz"
	},
	{
		"tel": "18299890800",
		"points": "2",
		"name": "Ismael Muñoz Castillo"
	},
	{
		"tel": "18496214248",
		"points": "2",
		"name": "Gabriela Santana"
	},
	{
		"tel": "18097809413",
		"points": "2",
		"name": "Flor Jimenez"
	},
	{
		"tel": "18298823133",
		"points": "2",
		"name": "Sajaira Margarita Jimenez Blanco"
	},
	{
		"tel": "18096076638",
		"points": "2",
		"name": "Marleny Ramirez"
	},
	{
		"tel": "18099033380",
		"points": "2",
		"name": "Esqueily Rosa"
	},
	{
		"tel": "18098836006",
		"points": "2",
		"name": "Gladys Díaz"
	},
	{
		"tel": "18295266165",
		"points": "2",
		"name": "Angelica Adon"
	},
	{
		"tel": "18094058912",
		"points": "2",
		"name": " "
	},
	{
		"tel": "18293013739",
		"points": "2",
		"name": "Sarah Mirt"
	},
	{
		"tel": "18293714807",
		"points": "2",
		"name": "Leo Hernández"
	},
	{
		"tel": "18098601281",
		"points": "2",
		"name": "Rosa Lida Marte Rodriguez"
	},
	{
		"tel": "18297664246",
		"points": "2",
		"name": "Yaneida Paez"
	},
	{
		"tel": "18093546883",
		"points": "2",
		"name": "Beily Castellanos"
	},
	{
		"tel": "18094056604",
		"points": "2",
		"name": "Eddy Arias"
	},
	{
		"tel": "18492848168",
		"points": "2",
		"name": "Ana María Rodríguez"
	},
	{
		"tel": "18294642507",
		"points": "2",
		"name": "Sergio Gil"
	},
	{
		"tel": "18097190846",
		"points": "2",
		"name": "Ramón Mendez"
	},
	{
		"tel": "18296408904",
		"points": "2",
		"name": "Estaury Encarnación"
	},
	{
		"tel": "18498789950",
		"points": "2",
		"name": "Ricardo Vasquez"
	},
	{
		"tel": "18094011810",
		"points": "2",
		"name": "Mayra Montero"
	},
	{
		"tel": "18493604395",
		"points": "2",
		"name": "Carlos Gil"
	},
	{
		"tel": "19734534602",
		"points": "2",
		"name": " "
	},
	{
		"tel": "18094403651",
		"points": "2",
		"name": "Starling Alcantara"
	},
	{
		"tel": "18298788743",
		"points": "2",
		"name": "Bladimir Adames"
	},
	{
		"tel": "18099353763",
		"points": "2",
		"name": "George Junior Acero Angomas"
	},
	{
		"tel": "18292839490",
		"points": "2",
		"name": "Jessca Decamp"
	},
	{
		"tel": "18492151118",
		"points": "2",
		"name": "Elizabeth Méndez Polanco"
	},
	{
		"tel": "18494082575",
		"points": "2",
		"name": "Santos Ramirez"
	},
	{
		"tel": "18296373635",
		"points": "2",
		"name": "Madeline Quiroz"
	},
	{
		"tel": "18496304638",
		"points": "2",
		"name": "José Yánez"
	},
	{
		"tel": "18098543294",
		"points": "2",
		"name": "Natividad Hernandez Sosa"
	},
	{
		"tel": "18292858182",
		"points": "2",
		"name": "Winston Rivera Canahuate"
	},
	{
		"tel": "18097169366",
		"points": "2",
		"name": "Fatima Moquete"
	},
	{
		"tel": "18495690321",
		"points": "2",
		"name": "Pamela Romero"
	},
	{
		"tel": "18492721416",
		"points": "2",
		"name": "Mar Rodriguez"
	},
	{
		"tel": "18093197774",
		"points": "2",
		"name": "Juan Demorizi Tavares"
	},
	{
		"tel": "18098616989",
		"points": "2",
		"name": "Raul Hernandez"
	},
	{
		"tel": "18498804333",
		"points": "2",
		"name": "Ariadna Arguelles"
	},
	{
		"tel": "18496335430",
		"points": "2",
		"name": "Miguel Angel Ruiz"
	},
	{
		"tel": "18297524104",
		"points": "2",
		"name": "Jhonatan Difo D'Eoleo"
	},
	{
		"tel": "18299708020",
		"points": "2",
		"name": "Justo Ramírez"
	},
	{
		"tel": "18294400340",
		"points": "2",
		"name": "Fedrik Encarnacion"
	},
	{
		"tel": "18298821005",
		"points": "2",
		"name": "Celia Lopez"
	},
	{
		"tel": "18492662402",
		"points": "2",
		"name": "Gabriela Alcántara"
	},
	{
		"tel": "18092535653",
		"points": "2",
		"name": "Yeni Martinez"
	},
	{
		"tel": "18299045723",
		"points": "2",
		"name": "Wilkaira Terrero"
	},
	{
		"tel": "18099782265",
		"points": "2",
		"name": "Emmanuel Y Daniel Reyes"
	},
	{
		"tel": "18298377774",
		"points": "2",
		"name": "Randy Luciano"
	},
	{
		"tel": "18097037050",
		"points": "2",
		"name": " "
	},
	{
		"tel": "13074592214",
		"points": "2",
		"name": "Mohamed Ali"
	},
	{
		"tel": "18099028216",
		"points": "2",
		"name": "Stevens Pipin"
	},
	{
		"tel": "18093185767",
		"points": "2",
		"name": "Grey Jimenez"
	},
	{
		"tel": "18496522862",
		"points": "2",
		"name": "Lizbeth Castro"
	},
	{
		"tel": "18097098666",
		"points": "2",
		"name": "Jeremy Company In"
	},
	{
		"tel": "18094670610",
		"points": "2",
		"name": "Juan Ferreiras"
	},
	{
		"tel": "18298830282",
		"points": "2",
		"name": "Luis Diaz"
	},
	{
		"tel": "18492078588",
		"points": "2",
		"name": "Luisanna Blanco"
	},
	{
		"tel": "18498555652",
		"points": "2",
		"name": "Emmanuel Cepeda Almonte"
	},
	{
		"tel": "18497073761",
		"points": "2",
		"name": "Tania Santana"
	},
	{
		"tel": "18298633420",
		"points": "2",
		"name": "Helen Gonzalez"
	},
	{
		"tel": "18295856744",
		"points": "2",
		"name": "Miguel Guerrero"
	},
	{
		"tel": "18498022797",
		"points": "2",
		"name": "Katherine Johanna Aybar Peña"
	},
	{
		"tel": "18293798588",
		"points": "2",
		"name": "Michell Betances Amadis"
	},
	{
		"tel": "18298155415",
		"points": "2",
		"name": "Roslay Marchese"
	},
	{
		"tel": "18097030667",
		"points": "2",
		"name": "Lucy Duran"
	},
	{
		"tel": "18299692326",
		"points": "2",
		"name": "Magdalena Meregildo Ogando"
	},
	{
		"tel": "18293406264",
		"points": "2",
		"name": "Katherine Rodriguez"
	},
	{
		"tel": "18097987946",
		"points": "2",
		"name": "Patsy Lopez"
	},
	{
		"tel": "18492856952",
		"points": "2",
		"name": "Nicole Herrera"
	},
	{
		"tel": "18293609168",
		"points": "2",
		"name": "Susan Diroche"
	},
	{
		"tel": "18299198998",
		"points": "2",
		"name": "Cesar González"
	},
	{
		"tel": "18299724789",
		"points": "2",
		"name": "Celinet Capellan"
	},
	{
		"tel": "18493510566",
		"points": "2",
		"name": "Luis Rossi"
	},
	{
		"tel": "18099837222",
		"points": "2",
		"name": "Gabriela Morillo Méndez"
	},
	{
		"tel": "18292786659",
		"points": "2",
		"name": "Manuel Perez"
	},
	{
		"tel": "18097779369",
		"points": "2",
		"name": "Anabel Reyes"
	},
	{
		"tel": "18099646354",
		"points": "2",
		"name": "Miguel Angel Encarnación"
	},
	{
		"tel": "18097088779",
		"points": "2",
		"name": "Yelena Rodriguez"
	},
	{
		"tel": "18292914259",
		"points": "2",
		"name": "Yeniffer Zarzuela"
	},
	{
		"tel": "18096091205",
		"points": "2",
		"name": "Marielba Osoria"
	},
	{
		"tel": "19543170000",
		"points": "2",
		"name": "Nezay1 0000 Bomba Shell"
	},
	{
		"tel": "18098511111",
		"points": "2",
		"name": "Genela Hernández"
	},
	{
		"tel": "18099013562",
		"points": "2",
		"name": "Virginia Pavonessa"
	},
	{
		"tel": "18299775894",
		"points": "2",
		"name": "Reyna Isabel Fortunato"
	},
	{
		"tel": "18092588434",
		"points": "2",
		"name": "Alfred De La Rosa"
	},
	{
		"tel": "18494098413",
		"points": "2",
		"name": "Jennifer Corona"
	},
	{
		"tel": "18294268766",
		"points": "2",
		"name": "Sawilka Reyes"
	},
	{
		"tel": "18097770793",
		"points": "2",
		"name": "J V"
	},
	{
		"tel": "18295591962",
		"points": "2",
		"name": "Yolanda Yolanda"
	},
	{
		"tel": "18298055515",
		"points": "2",
		"name": "Mayrelin Gonzalez"
	},
	{
		"tel": "18293876942",
		"points": "2",
		"name": "Betsi Angely Mata"
	},
	{
		"tel": "18492202086",
		"points": "2",
		"name": "Raquel Mota"
	},
	{
		"tel": "18297475826",
		"points": "2",
		"name": "Edwin Berroa"
	},
	{
		"tel": "18098909067",
		"points": "2",
		"name": "Eli Hernández"
	},
	{
		"tel": "18492607791",
		"points": "2",
		"name": "Jessica Almanzar"
	},
	{
		"tel": "18497541122",
		"points": "2",
		"name": "Elvis Gonzales"
	},
	{
		"tel": "18296778535",
		"points": "2",
		"name": "Bethania Taveras"
	},
	{
		"tel": "18298515549",
		"points": "2",
		"name": "Perla Yanibel Melo Brito"
	},
	{
		"tel": "18092710598",
		"points": "2",
		"name": "Ray Lorenzo Ortiz"
	},
	{
		"tel": "18726666355",
		"points": "2",
		"name": "Nezay1 6355 Bomba Shell"
	},
	{
		"tel": "18098812909",
		"points": "2",
		"name": "Verónica Cueto"
	},
	{
		"tel": "18299701759",
		"points": "2",
		"name": "Cristian J. Arciniega"
	},
	{
		"tel": "18292651940",
		"points": "2",
		"name": "Ines De Aza"
	},
	{
		"tel": "18297300200",
		"points": "2",
		"name": "Yuniorr Tavara"
	},
	{
		"tel": "18098013331",
		"points": "2",
		"name": "Santa Rodriguez"
	},
	{
		"tel": "18092576124",
		"points": "2",
		"name": "Priscila Almonte"
	},
	{
		"tel": "18492525013",
		"points": "2",
		"name": "Edwar Salomon"
	},
	{
		"tel": "18297717914",
		"points": "2",
		"name": "Francisco Vasquez"
	},
	{
		"tel": "18297577586",
		"points": "2",
		"name": "Vanessa Armengot"
	},
	{
		"tel": "18293755967",
		"points": "2",
		"name": "Damerlyn Geronimo"
	},
	{
		"tel": "18493445031",
		"points": "2",
		"name": "Orlando Betances"
	},
	{
		"tel": "18094844247",
		"points": "2",
		"name": "Glenny Morillo"
	},
	{
		"tel": "18493426088",
		"points": "2",
		"name": "Hector Orozco"
	},
	{
		"tel": "18298466027",
		"points": "2",
		"name": "Marislanda Vicente"
	},
	{
		"tel": "18492615323",
		"points": "2",
		"name": "Wendy Adames"
	},
	{
		"tel": "18293807990",
		"points": "2",
		"name": "Angela Vasquez"
	},
	{
		"tel": "18297540430",
		"points": "2",
		"name": "Camila Santiago"
	},
	{
		"tel": "18298053374",
		"points": "2",
		"name": "Steph Rodriguez"
	},
	{
		"tel": "18494078208",
		"points": "2",
		"name": "Felix Tiburcio"
	},
	{
		"tel": "18496235691",
		"points": "2",
		"name": "Silenny Ramón Brioso"
	},
	{
		"tel": "18492030336",
		"points": "2",
		"name": "Lesly Jacques"
	},
	{
		"tel": "18499176996",
		"points": "2",
		"name": "Katherinne Rodriguez"
	},
	{
		"tel": "18297722312",
		"points": "2",
		"name": "Francelys Objio"
	},
	{
		"tel": "18299706187",
		"points": "2",
		"name": "Luis Cruz"
	},
	{
		"tel": "18097914128",
		"points": "2",
		"name": "Manuel Gomez"
	},
	{
		"tel": "18297544217",
		"points": "2",
		"name": "Cristina Sosa"
	},
	{
		"tel": "18298393952",
		"points": "2",
		"name": "Masiel Jimenez"
	},
	{
		"tel": "18096576813",
		"points": "2",
		"name": "Benja Quiroz"
	},
	{
		"tel": "18294092490",
		"points": "2",
		"name": "Yosari Rojas"
	},
	{
		"tel": "18296655745",
		"points": "2",
		"name": "Jiezi Mateo"
	},
	{
		"tel": "18097611331",
		"points": "2",
		"name": "Angie Cuevas"
	},
	{
		"tel": "18496208783",
		"points": "2",
		"name": "Daniel De Leon"
	},
	{
		"tel": "18296038022",
		"points": "2",
		"name": "Karina Ramírez"
	},
	{
		"tel": "18292975128",
		"points": "2",
		"name": "Enmanuel Ogando"
	},
	{
		"tel": "18295126116",
		"points": "2",
		"name": "Dioscar Castro"
	},
	{
		"tel": "18295693837",
		"points": "2",
		"name": "Luz Maria Liriano"
	},
	{
		"tel": "18099891497",
		"points": "2",
		"name": "Diana Montero"
	},
	{
		"tel": "18295804977",
		"points": "2",
		"name": "Evelyn Perez"
	},
	{
		"tel": "18498851843",
		"points": "2",
		"name": "Eriberto Peña Silverio"
	},
	{
		"tel": "18098859447",
		"points": "2",
		"name": "Maikel Jimenez"
	},
	{
		"tel": "18298063156",
		"points": "2",
		"name": "Yary Tejada"
	},
	{
		"tel": "18494522557",
		"points": "2",
		"name": "Maruja Morel"
	},
	{
		"tel": "18092352002",
		"points": "2",
		"name": "Angel Heredia De Jesús"
	},
	{
		"tel": "18093300911",
		"points": "2",
		"name": "Alejandro Camilo"
	},
	{
		"tel": "18296105341",
		"points": "2",
		"name": "Lucinda Ventura"
	},
	{
		"tel": "18498537183",
		"points": "2",
		"name": "Stephanie Sanchez"
	},
	{
		"tel": "18299893642",
		"points": "2",
		"name": "Ramon Angomas"
	},
	{
		"tel": "18494041489",
		"points": "2",
		"name": "Erolin Alvarez"
	},
	{
		"tel": "18295151729",
		"points": "2",
		"name": "Jonatan Gonzalez"
	},
	{
		"tel": "18299627566",
		"points": "2",
		"name": "Wood Isaac Cetoute"
	},
	{
		"tel": "18298182528",
		"points": "2",
		"name": "Camila Brito"
	},
	{
		"tel": "19143014285",
		"points": "2",
		"name": "Kewris Miguel"
	},
	{
		"tel": "18092680035",
		"points": "2",
		"name": "Jeicel Lovera"
	},
	{
		"tel": "18094381407",
		"points": "2",
		"name": "Monica Esmeralda Figuereo De Solis"
	},
	{
		"tel": "18099653313",
		"points": "2",
		"name": "Laura Marte"
	},
	{
		"tel": "18494511869",
		"points": "2",
		"name": "Jorge Then"
	},
	{
		"tel": "18092153109",
		"points": "2",
		"name": "Ana Abreu"
	},
	{
		"tel": "18092495025",
		"points": "2",
		"name": "Jossual Rodriguez"
	},
	{
		"tel": "18297961043",
		"points": "2",
		"name": "Yajaira Severino"
	},
	{
		"tel": "18092536399",
		"points": "2",
		"name": "Maria Herreras"
	},
	{
		"tel": "18298262790",
		"points": "2",
		"name": "Ronald Tejada"
	},
	{
		"tel": "18498515255",
		"points": "2",
		"name": "Joas Eliezer Gonzalez Vargas"
	},
	{
		"tel": "18298778655",
		"points": "2",
		"name": "Lisbet Reyes"
	},
	{
		"tel": "18496512178",
		"points": "2",
		"name": "Bryan Lebron"
	},
	{
		"tel": "18493610952",
		"points": "2",
		"name": "Yarleni Marte"
	},
	{
		"tel": "18298833068",
		"points": "2",
		"name": "Moises Messina"
	},
	{
		"tel": "18299602202",
		"points": "2",
		"name": "Lourenz Mateo"
	},
	{
		"tel": "18095169654",
		"points": "2",
		"name": "Rosario Vargas"
	},
	{
		"tel": "18496242207",
		"points": "2",
		"name": "J Cuevas"
	},
	{
		"tel": "18093050418",
		"points": "2",
		"name": "Marco Antonio Jimenez"
	},
	{
		"tel": "19734571768",
		"points": "2",
		"name": "Yefri "
	},
	{
		"tel": "18295785455",
		"points": "2",
		"name": "Auribel Perez"
	},
	{
		"tel": "18296292797",
		"points": "2",
		"name": "Rafael Sosa"
	},
	{
		"tel": "18097058084",
		"points": "2",
		"name": "Gabriela De La Paz"
	},
	{
		"tel": "18292863090",
		"points": "2",
		"name": "Andrea Antonio"
	},
	{
		"tel": "18098014333",
		"points": "2",
		"name": "Moises Colón Cruz"
	},
	{
		"tel": "18299385576",
		"points": "2",
		"name": "Anny Castillo"
	},
	{
		"tel": "18297635978",
		"points": "2",
		"name": "Nicole Valdez Valdez"
	},
	{
		"tel": "18296453218",
		"points": "2",
		"name": "Cristal Cornielle"
	},
	{
		"tel": "18098534612",
		"points": "2",
		"name": "Luis Zarete"
	},
	{
		"tel": "18098280248",
		"points": "2",
		"name": "Reina Mieses"
	},
	{
		"tel": "18093180452",
		"points": "2",
		"name": "Yisbell Cabrera Diaz"
	},
	{
		"tel": "18293052349",
		"points": "2",
		"name": "Daniel Paulino"
	},
	{
		"tel": "18495420043",
		"points": "2",
		"name": "Indiana Duran"
	},
	{
		"tel": "18099748921",
		"points": "2",
		"name": "Mildred Liriano"
	},
	{
		"tel": "18099811178",
		"points": "2",
		"name": "Kenndy Alcantara"
	},
	{
		"tel": "18294203015",
		"points": "2",
		"name": "Herby Charles"
	},
	{
		"tel": "18294121230",
		"points": "2",
		"name": "Yefferson Espinal"
	},
	{
		"tel": "18293170581",
		"points": "2",
		"name": "Indhira Amparo Hamburgos"
	},
	{
		"tel": "18297175386",
		"points": "2",
		"name": "Adriely Florentino"
	},
	{
		"tel": "18297094695",
		"points": "2",
		"name": "Siria Alcantara"
	},
	{
		"tel": "18293015457",
		"points": "2",
		"name": "Waldy Mateo Ff"
	},
	{
		"tel": "18295434887",
		"points": "2",
		"name": "Rafael Martinez"
	},
	{
		"tel": "18294043493",
		"points": "2",
		"name": "Sarah González"
	},
	{
		"tel": "18094130416",
		"points": "2",
		"name": "Cris Mercedes"
	},
	{
		"tel": "18294275335",
		"points": "2",
		"name": "Hander Esmerlyn Beltre Canela"
	},
	{
		"tel": "18493536444",
		"points": "2",
		"name": "Fraylin Santos"
	},
	{
		"tel": "18297918582",
		"points": "2",
		"name": "Domarlyn Contreras"
	},
	{
		"tel": "18092067168",
		"points": "2",
		"name": "Hilario Hernandez"
	},
	{
		"tel": "18498861507",
		"points": "2",
		"name": "Dahiana Cordero"
	},
	{
		"tel": "18294443730",
		"points": "2",
		"name": "Yireimy Peralta"
	},
	{
		"tel": "18494082710",
		"points": "2",
		"name": "Yileny Frias Garcia"
	},
	{
		"tel": "18293413272",
		"points": "2",
		"name": "Fior Mejia"
	},
	{
		"tel": "18492587066",
		"points": "2",
		"name": "Francina Martinez"
	},
	{
		"tel": "18297298071",
		"points": "2",
		"name": "Jehiel Febrier"
	},
	{
		"tel": "18294498142",
		"points": "2",
		"name": "Suhail Rosario"
	},
	{
		"tel": "18293296510",
		"points": "2",
		"name": "Stiven De La Cruz"
	},
	{
		"tel": "18299190111",
		"points": "2",
		"name": "Maria Regalado"
	},
	{
		"tel": "18297151213",
		"points": "2",
		"name": "Ana Cinthia"
	}
]